savesyndrom/__init__.py
savesyndrom/__main__.py
savesyndrom/activewindow.py
savesyndrom/keylogger.py
savesyndrom/settings.py
savesyndrom/gui/__init__.py
savesyndrom/gui/main.py
savesyndrom/gui/show.py
savesyndrom-0.1.2.dist-info/METADATA
savesyndrom-0.1.2.dist-info/WHEEL
savesyndrom-0.1.2.dist-info/top_level.txt
savesyndrom-0.1.2.dist-info/RECORD
