Metadata-Version: 2.1
Name: savesyndrom
Version: 0.1.2
Summary: UNKNOWN
Home-page: https://github.com/OlegYurchik/savesyndrom
Author: Oleg Yurchik
Author-email: oleg.yurchik@protonmail.com
License: UNKNOWN
Platform: UNKNOWN
Requires-Python: >=3.6
Requires-Dist: PyQt5
Requires-Dist: keyboard
Requires-Dist: pywin32
